{
  "addonName": "cisco_cisco-cloud-observability-operators",
  "type": "observability",
  "addonVersions": [
    {
      "addonVersion": "v1.16.255-eksbuild.1",
      "architecture": [
        "amd64",
        "arm64"
      ],
      "compatibilities": [
        {
          "clusterVersion": "1.28",
          "platformVersions": [
            "*"
          ],
          "defaultVersion": true
        },
        {
          "clusterVersion": "1.27",
          "platformVersions": [
            "*"
          ],
          "defaultVersion": true
        },
        {
          "clusterVersion": "1.26",
          "platformVersions": [
            "*"
          ],
          "defaultVersion": true
        },
        {
          "clusterVersion": "1.25",
          "platformVersions": [
            "*"
          ],
          "defaultVersion": true
        },
        {
          "clusterVersion": "1.24",
          "platformVersions": [
            "*"
          ],
          "defaultVersion": true
        },
        {
          "clusterVersion": "1.23",
          "platformVersions": [
            "*"
          ],
          "defaultVersion": true
        }
      ],
      "requiresConfiguration": true,
      "requiresIamPermissions": false
    }
  ],
  "publisher": "Cisco Systems, Inc.",
  "owner": "aws-marketplace",
  "marketplaceInformation": {
    "productId": "38179cb1-c95c-4f96-ad48-756876047f26",
    "productUrl": "https://aws.amazon.com/marketplace/pp/prodview-iyryefaozooow"
  }
}
